{
    "version": "40.104.3",
    "description": "aardio 编程语言，专注于桌面软件快速开发",
    "homepage": "https://www.aardio.com/",
    "license": "Freeware",
    "url": "https://d.aardio.com/ide/aardio.7z",
    "hash": "1e2f42c58177400a0277642daa171b3299f003caf152c0cff4f8b3e6d079d9d6",
    "bin": "aardio.exe",
    "shortcuts": [
        [
            "aardio.exe",
            "aardio"
        ]
    ],
    "persist": [
        "config",
        "download",
        "project",
        "codes\\我的代码段"
    ],
    "checkver": {
        "url": "http://d.aardio.com/ide/check/",
        "jsonpath": "$.version"
    },
    "autoupdate": {
        "url": "https://d.aardio.com/ide/aardio.7z"
    }
}
