{
    "version": "38.5.6",
    "description": "aardio 编程语言，专注于桌面软件快速开发",
    "homepage": "https://www.aardio.com/",
    "license": "Freeware",
    "url": "https://d.aardio.com/ide/aardio.7z",
    "hash": "29f2d347ba9eb8fc0c66e2b3217a637f2dd093734faa1c3dd818bb4c190a790a",
    "bin": "aardio.exe",
    "shortcuts": [
        [
            "aardio.exe",
            "aardio"
        ]
    ],
    "persist": [
        "config",
        "download",
        "project",
        "codes\\我的代码段"
    ],
    "checkver": {
        "url": "http://d.aardio.com/ide/check/",
        "jsonpath": "$.version"
    },
    "autoupdate": {
        "url": "https://d.aardio.com/ide/aardio.7z"
    }
}
