{
    "version": "8.0.1",
    "description": "A full-featured painting tool with a huge set of predefined realistic brushes to paint creatively or just experiment.",
    "homepage": "https://www.artweaver.de/en",
    "license": "Liteware",
    "url": "https://www.artweaver.de/direct/Artweaver.exe#/Installer.exe",
    "hash": "e2358bc52be5a2e33b10a6e003a1fe63b93c5e4f786d39a8b23cf688fabe93ea",
    "innosetup": true,
    "shortcuts": [
        [
            "Artweaver.exe",
            "Artweaver Free"
        ]
    ],
    "pre_install": "if (!(Test-Path \"$persist_dir\\Artweaver.ini\")) { Set-Content -Encoding ASCII -Path \"$dir\\Artweaver.ini\" -Value '[Software\\Artweaver Free\\7.0\\Settings]', 'UpdateEnabled=0' }",
    "persist": "Artweaver.ini",
    "checkver": {
        "url": "https://www.artweaver.de/en/download",
        "regex": "\\| Version: ([\\d.]+)"
    },
    "autoupdate": {
        "url": "https://www.artweaver.de/direct/Artweaver.exe#/Installer.exe"
    }
}
