{
    "version": "2.3.24.0",
    "description": "Extend the function of ASF (ArchiSteamFarm), add several practical commands",
    "homepage": "https://github.com/chr233/ASFEnhance",
    "license": "AGPL-3.0-only",
    "depends": "lemon/archisteamfarm",
    "architecture": {
        "64bit": {
            "url": "https://github.com/chr233/ASFEnhance/releases/download/2.3.24.0/ASFEnhance.zip",
            "hash": "6d2a97b3c87be36057511bae1c491cba0aa5be6a49b10f2e0e9f904b7267ede2"
        }
    },
    "installer": {
        "script": "if (installed 'archisteamfarm' $global) {Copy-Item \"$dir\\ASFEnhance.dll\" \"$(appdir archisteamfarm $global)\\current\\plugins\"} else { error 'Please install `archisteamfarm` first, then reinstall `asfenhance`.'}"
    },
    "uninstaller": {
        "script": "if (installed 'archisteamfarm' $global) {Remove-Item \"$(appdir archisteamfarm $global)\\current\\plugins\\ASFEnhance.dll\"}"
    },
    "checkver": "github",
    "autoupdate": {
        "architecture": {
            "64bit": {
                "url": "https://github.com/chr233/ASFEnhance/releases/download/$version/ASFEnhance.zip"
            }
        }
    }
}
