{
    "version": "6.12.7",
    "description": "The open source high performance ELT framework powered by Apache Arrow.",
    "homepage": "https://cloudquery.io/",
    "license": "MPL-2.0",
    "architecture": {
        "64bit": {
            "url": "https://github.com/cloudquery/cloudquery/releases/download/cli-v6.12.7/cloudquery_windows_amd64.zip",
            "hash": "b61fa019ce2f13a4c7e0394992d81830c3b6e359eb533aa9ea77843f217b49b5"
        }
    },
    "bin": "cloudquery.exe",
    "checkver": {
        "url": "https://raw.githubusercontent.com/cloudquery/cloudquery/refs/heads/main/.release-please-manifest.json",
        "jsonpath": "$.cli"
    },
    "autoupdate": {
        "architecture": {
            "64bit": {
                "url": "https://github.com/cloudquery/cloudquery/releases/download/cli-v$version/cloudquery_windows_amd64.zip"
            }
        },
        "hash": {
            "url": "$baseurl/checksums.txt"
        }
    }
}
