{
    "version": "18",
    "description": "A lossless data compression program aimed at optimizing compression ratio at the cost of high CPU/memory usage.",
    "homepage": "http://www.byronknoll.com/cmix.html",
    "license": "GPL-3.0-only",
    "architecture": {
        "64bit": {
            "url": "http://www.byronknoll.com/cmix-v18-windows.zip",
            "hash": "a7cdddbb1fc10666eb8101efbba92297924f986f50c7c419e3606eea2a866e3e"
        }
    },
    "extract_dir": "cmix",
    "bin": "cmix.exe",
    "checkver": {
        "github": "https://github.com/byronknoll/cmix"
    },
    "autoupdate": {
        "architecture": {
            "64bit": {
                "url": "http://www.byronknoll.com/cmix-v$version-windows.zip"
            }
        }
    }
}
