{
    "version": "3.2.2",
    "description": "现代且强大的串口助手",
    "homepage": "https://gitee.com/xenkuo/comNG",
    "license": "MIT",
    "architecture": {
        "64bit": {
            "url": "https://gitee.com/xenkuo/comNG/releases/download/v3.2.2/comNG-3.2.2%20Setup.exe#/dl.7z",
            "hash": "bd5a4f127ecfca833127ed6a8805ed1e189c4a61cceb552c8914a42b99df23ff"
        }
    },
    "pre_install": [
        "Get-ChildItem -Path \"$dir\" | Where-Object { $_.Name -NotLike 'comNG-*-full.nupkg' } | Remove-Item",
        "Expand-7zipArchive -Path \"$dir\\comNG-*-full.nupkg\" -DestinationPath \"$dir\" -ExtractDir \"lib\\net45\" -Removal"
    ],
    "shortcuts": [
        [
            "comNG.exe",
            "comNG"
        ]
    ],
    "post_uninstall": "if ($purge) { Remove-Item \"$env:APPDATA\\comNG\", \"$env:LOCALAPPDATA\\comNG\" -Force -Recurse -ErrorAction SilentlyContinue }",
    "notes": [
        "comNG is NOT portable.",
        "Settings are stored in '%APPDATA%\\comNG', and will be purged during uninstallation."
    ],
    "checkver": {
        "url": "https://gitee.com/xenkuo/comNG/tags.atom",
        "regex": "Repository/\\d+/v(.+?)<"
    },
    "autoupdate": {
        "architecture": {
            "64bit": {
                "url": "https://gitee.com/xenkuo/comNG/releases/download/v$version/comNG-$version%20Setup.exe#/dl.7z"
            }
        }
    }
}
