{
    "version": "1.2.3.1718",
    "description": "A universal pasteboard across devices.",
    "homepage": "https://crosspaste.com/",
    "license": "AGPL-3.0-only",
    "architecture": {
        "64bit": {
            "url": "https://github.com/CrossPaste/crosspaste-desktop/releases/download/1.2.3.1718/crosspaste-1.2.3-1718-windows-amd64.zip",
            "hash": "a48e263323e5369fe201c380228e1d3ca2d68fdc5321647805599b6e8642e89f"
        }
    },
    "shortcuts": [
        [
            "bin\\CrossPaste.exe",
            "CrossPaste"
        ]
    ],
    "checkver": {
        "github": "https://github.com/CrossPaste/crosspaste-desktop"
    },
    "notes": "CrossPaste is NOT portable.",
    "autoupdate": {
        "architecture": {
            "64bit": {
                "url": "https://github.com/CrossPaste/crosspaste-desktop/releases/download/$version/crosspaste-$matchHead-$buildVersion-windows-amd64.zip"
            }
        },
        "hash": {
            "url": "$baseurl/checksum.txt"
        }
    }
}
