{
    "version": "1.0.5",
    "description": "A universal pasteboard across devices.",
    "homepage": "https://crosspaste.com/",
    "license": "AGPL-3.0-only",
    "architecture": {
        "64bit": {
            "url": "https://github.com/CrossPaste/crosspaste-desktop/releases/download/v1.0.5/crosspaste-1.0.5-838-windows-amd64.zip",
            "hash": "17b2a8d1a2f2c5a6f55b0d19242b126016f459b994415aa88d2792ed4530f129"
        }
    },
    "shortcuts": [
        [
            "bin\\CrossPaste.exe",
            "CrossPaste"
        ]
    ],
    "checkver": {
        "github": "https://github.com/CrossPaste/crosspaste-desktop"
    },
    "notes": "CrossPaste is NOT portable.",
    "autoupdate": {
        "architecture": {
            "64bit": {
                "url": "https://github.com/CrossPaste/crosspaste-desktop/releases/download/v$version/crosspaste-$version-838-windows-amd64.zip"
            }
        },
        "hash": {
            "url": "$baseurl/checksum.txt"
        }
    }
}
