{
    "version": "1.5.6",
    "description": "A command line tool for porting Excalidraw diagrams to Gliffy and draw.io.",
    "homepage": "https://github.com/sindrel/excalidraw-converter",
    "license": "MIT",
    "architecture": {
        "64bit": {
            "url": "https://github.com/sindrel/excalidraw-converter/releases/download/v1.5.6/excalidraw-converter_1.5.6_windows_amd64.zip",
            "hash": "1862968be1d0a598065ffe769b9bc0983937a221069c165684ca2be45a666346"
        }
    },
    "bin": "exconv.exe",
    "checkver": "github",
    "autoupdate": {
        "architecture": {
            "64bit": {
                "url": "https://github.com/sindrel/excalidraw-converter/releases/download/v$version/excalidraw-converter_$version_windows_amd64.zip"
            }
        },
        "hash": {
            "url": "$baseurl/excalidraw-converter_$version_checksums.txt"
        }
    }
}
