{
    "version": "1.4.326",
    "description": "An open-source framework for augmenting humans using AI.",
    "homepage": "https://github.com/danielmiessler/fabric",
    "license": "MIT",
    "architecture": {
        "64bit": {
            "url": "https://github.com/danielmiessler/Fabric/releases/download/v1.4.326/fabric_Windows_x86_64.zip",
            "hash": "54f6124067c79aaee82f47dc8b37e512193294434ecc59bb17f8d8ae9659ed20"
        },
        "32bit": {
            "url": "https://github.com/danielmiessler/Fabric/releases/download/v1.4.326/fabric_Windows_i386.zip",
            "hash": "71f88846875eb43827fe59e01509e8f323bff561315f1e9fb2b0994a109934fc"
        },
        "arm64": {
            "url": "https://github.com/danielmiessler/Fabric/releases/download/v1.4.326/fabric_Windows_arm64.zip",
            "hash": "e416c1f47227ef73b9537569bb73422da4cdf92aa5111929702fa023ebed019e"
        }
    },
    "bin": "fabric.exe",
    "checkver": "github",
    "autoupdate": {
        "architecture": {
            "64bit": {
                "url": "https://github.com/danielmiessler/Fabric/releases/download/v$version/fabric_Windows_x86_64.zip"
            },
            "32bit": {
                "url": "https://github.com/danielmiessler/Fabric/releases/download/v$version/fabric_Windows_i386.zip"
            },
            "arm64": {
                "url": "https://github.com/danielmiessler/Fabric/releases/download/v$version/fabric_Windows_arm64.zip"
            }
        },
        "hash": {
            "url": "$baseurl/fabric_$version_checksums.txt"
        }
    }
}
