{
    "version": "2.15.345",
    "description": "The commandline app for Files.com.",
    "homepage": "https://developers.files.com/cli/",
    "license": "MIT",
    "architecture": {
        "64bit": {
            "url": "https://github.com/Files-com/files-cli/releases/download/v2.15.345/files-cli_windows_64bit.zip",
            "hash": "5ad8aab287096263164f6b82938a9038d18fcc4a0e9f4bfb79fef519467fa322"
        },
        "arm64": {
            "url": "https://github.com/Files-com/files-cli/releases/download/v2.15.345/files-cli_windows_arm64.zip",
            "hash": "fea4f7f3b60860ebc8e10b420e303544c57f39e94345436f012082fc3d5db229"
        }
    },
    "bin": "files-cli.exe",
    "checkver": {
        "github": "https://github.com/Files-com/files-cli"
    },
    "autoupdate": {
        "architecture": {
            "64bit": {
                "url": "https://github.com/Files-com/files-cli/releases/download/v$version/files-cli_windows_64bit.zip"
            },
            "arm64": {
                "url": "https://github.com/Files-com/files-cli/releases/download/v$version/files-cli_windows_arm64.zip"
            }
        },
        "hash": {
            "url": "$baseurl/checksums.txt"
        }
    }
}
