{
    "version": "4.75.1",
    "description": "A CLI tool for managing Fleet, an open-source platform for IT, security, and infrastructure teams.",
    "homepage": "https://fleetdm.com/",
    "license": {
        "identifier": "MIT",
        "url": "https://raw.githubusercontent.com/fleetdm/fleet/refs/heads/main/LICENSE"
    },
    "architecture": {
        "64bit": {
            "url": "https://github.com/fleetdm/fleet/releases/download/fleet-v4.75.1/fleetctl_v4.75.1_windows_amd64.zip",
            "extract_dir": "fleetctl_v4.75.1_windows_amd64",
            "hash": "9465a688d4ded8193490edd889f9859cefae3550eea5ab783558db370f5b3ed8"
        },
        "arm64": {
            "url": "https://github.com/fleetdm/fleet/releases/download/fleet-v4.75.1/fleetctl_v4.75.1_windows_arm64.zip",
            "extract_dir": "fleetctl_v4.75.1_windows_arm64",
            "hash": "4d6c09b7afa67ba3a129a2e9eeb9d8b45aa75c43cb70e4939c63f4570204ebf2"
        }
    },
    "bin": "fleetctl.exe",
    "checkver": {
        "url": "https://github.com/fleetdm/fleet/releases.atom",
        "regex": "Repository/\\d+/fleet-v(.+?)<"
    },
    "autoupdate": {
        "architecture": {
            "64bit": {
                "url": "https://github.com/fleetdm/fleet/releases/download/fleet-v$version/fleetctl_v$version_windows_amd64.zip",
                "extract_dir": "fleetctl_v$version_windows_amd64"
            },
            "arm64": {
                "url": "https://github.com/fleetdm/fleet/releases/download/fleet-v$version/fleetctl_v$version_windows_arm64.zip",
                "extract_dir": "fleetctl_v$version_windows_arm64"
            }
        },
        "hash": {
            "url": "$baseurl/checksums.txt"
        }
    }
}
