{
    "version": "1.0.209",
    "description": "A stable and production ready opensource solution to automate iOS device.",
    "homepage": "https://github.com/danielpaulus/go-ios",
    "license": "MIT",
    "architecture": {
        "64bit": {
            "url": "https://github.com/danielpaulus/go-ios/releases/download/v1.0.209/go-ios-win.zip",
            "hash": "5326753c9f12f30911d6809005cd143e368038ec3dbd576217cfce76e0132c69"
        }
    },
    "bin": "ios.exe",
    "checkver": "github",
    "autoupdate": {
        "architecture": {
            "64bit": {
                "url": "https://github.com/danielpaulus/go-ios/releases/download/v$version/go-ios-win.zip"
            }
        }
    }
}
