{
    "version": "0.27.30",
    "description": "A terminal-based user interface application that manages and synchronizes kubectl port-forward configurations with ease.",
    "homepage": "https://kftray.app/",
    "license": "GPL-3.0-only",
    "architecture": {
        "64bit": {
            "url": "https://github.com/hcavarsan/kftray/releases/download/v0.27.30/kftui_windows_x86_64.exe#/kftui.exe",
            "hash": "440e752577d133ec7a13e4c7f81c9a8216a21c82a3fe4309aa4906bcb7b6288f"
        },
        "32bit": {
            "url": "https://github.com/hcavarsan/kftray/releases/download/v0.27.30/kftui_windows_x86.exe#/kftui.exe",
            "hash": "42b4b04c2e443a3ee89c9e04abb7db07d6803231ddd375505550c1e22f1465d3"
        }
    },
    "bin": "kftui.exe",
    "checkver": {
        "github": "https://github.com/hcavarsan/kftray"
    },
    "autoupdate": {
        "architecture": {
            "64bit": {
                "url": "https://github.com/hcavarsan/kftray/releases/download/v$version/kftui_windows_x86_64.exe#/kftui.exe"
            },
            "32bit": {
                "url": "https://github.com/hcavarsan/kftray/releases/download/v$version/kftui_windows_x86.exe#/kftui.exe"
            }
        }
    }
}
