{
    "version": "2.0.4",
    "description": "A build system and monorepo management tool for the web ecosystem, written in Rust.",
    "homepage": "https://moonrepo.dev/moon",
    "license": "MIT",
    "architecture": {
        "64bit": {
            "url": "https://github.com/moonrepo/moon/releases/download/v2.0.4/moon_cli-x86_64-pc-windows-msvc.zip",
            "hash": "90935b1a30cf7696fe34cfa72e8c36833629f5b733c0c24f30d294c6434e3b95"
        }
    },
    "bin": [
        "moon.exe",
        "moonx.exe"
    ],
    "checkver": {
        "url": "https://github.com/moonrepo/moon/releases.atom",
        "regex": "Repository/\\d+/v(.+?)<"
    },
    "autoupdate": {
        "architecture": {
            "64bit": {
                "url": "https://github.com/moonrepo/moon/releases/download/v$version/moon_cli-x86_64-pc-windows-msvc.zip"
            }
        },
        "hash": {
            "url": "$url.sha256"
        }
    }
}
