{
    "version": "0.22.1",
    "description": "A human-friendly companion that helps to interact with NEAR Protocol from command line.",
    "homepage": "https://github.com/near/near-cli-rs",
    "license": "Apache-2.0|MIT",
    "architecture": {
        "64bit": {
            "url": "https://github.com/near/near-cli-rs/releases/download/v0.22.1/near-cli-rs-x86_64-pc-windows-msvc.tar.gz",
            "extract_dir": "near-cli-rs-x86_64-pc-windows-msvc",
            "hash": "5547b82ac06f8f13c074f6be383ddf9df9c0fc6e8649852c90d118f3958d5166"
        }
    },
    "bin": "near.exe",
    "checkver": "github",
    "autoupdate": {
        "architecture": {
            "64bit": {
                "url": "https://github.com/near/near-cli-rs/releases/download/v$version/near-cli-rs-x86_64-pc-windows-msvc.tar.gz"
            }
        },
        "hash": {
            "url": "$url.sha256"
        }
    }
}
