{
    "version": "5.15",
    "description": "NetAssist网络调试助手是一款TCP/IP网络调试工具，支持UDP/TCP/MQTT等应用协议",
    "homepage": "https://www.cmsoft.cn/resource/102.html",
    "license": "Liteware",
    "url": "https://free.cmsoft.cn/download/cmsoft/assistant/netassist5.15.zip",
    "hash": "addc35bbc1fddd92a7bc672216e93c64686e514e410d5ab31c0b4e6ac8891885",
    "shortcuts": [
        [
            "NetAssist.exe",
            "NetAssist"
        ]
    ],
    "post_uninstall": [
        "if ($purge) { Remove-Item -Path 'HKCU:\\Software\\Cmsoft\\NetAssist' -ErrorAction SilentlyContinue }",
        "if ($purge) { Remove-Item \"$env:APPDATA\\Cmsoft\\netassist.sys\" -Force -Recurse -ErrorAction SilentlyContinue }"
    ],
    "checkver": {
        "regex": "\\[软件版本\\].+?>([\\d.]+)<"
    },
    "autoupdate": {
        "url": "https://free.cmsoft.cn/download/cmsoft/assistant/netassist$version.zip"
    }
}
