{
    "version": "0.38.1",
    "description": "Server for Oxen, a lightning fast data version control system for structured and unstructured machine learning datasets.",
    "homepage": "https://oxen.ai/",
    "license": "Apache-2.0",
    "architecture": {
        "64bit": {
            "url": "https://github.com/Oxen-AI/Oxen/releases/download/v0.38.1/oxen-server-windows-x86_64.exe.zip",
            "hash": "0f22fb9217a049e3b20e0cbd6ceb73d0a2de4c9c139e7fb7c4be8daec26127be"
        }
    },
    "bin": "oxen-server.exe",
    "checkver": {
        "github": "https://github.com/Oxen-AI/Oxen"
    },
    "autoupdate": {
        "architecture": {
            "64bit": {
                "url": "https://github.com/Oxen-AI/Oxen/releases/download/v$version/oxen-server-windows-x86_64.exe.zip"
            }
        }
    }
}
