{
    "version": "3.0.10.2",
    "description": "A CLI for Apache Pulsar written in Go.",
    "homepage": "https://github.com/streamnative/pulsarctl",
    "license": "Apache-2.0",
    "architecture": {
        "64bit": {
            "url": "https://github.com/streamnative/pulsarctl/releases/download/v3.0.10.2/pulsarctl-amd64-windows.tar.gz",
            "hash": "e7fe212045e248cea146a36c17c9cd4a7f5ccab35564893498f77a7d3dfc45db",
            "extract_dir": "pulsarctl-amd64-windows"
        },
        "32bit": {
            "url": "https://github.com/streamnative/pulsarctl/releases/download/v3.0.10.2/pulsarctl-386-windows.tar.gz",
            "hash": "59de12d8a416795e6b59f65da3ac486cc9af0df4eac6da81467db8ca94935070",
            "extract_dir": "pulsarctl-386-windows"
        }
    },
    "pre_install": "if (Test-Path \"$dir\\pulsarctl\") { Rename-Item -Path \"$dir\\pulsarctl\" -NewName \"$dir\\pulsarctl.exe\" }",
    "bin": "pulsarctl.exe",
    "checkver": {
        "url": "https://github.com/streamnative/pulsarctl/releases.atom",
        "regex": "Repository/\\d+/v(3\\.[\\d.]+)<"
    },
    "autoupdate": {
        "architecture": {
            "64bit": {
                "url": "https://github.com/streamnative/pulsarctl/releases/download/v$version/pulsarctl-amd64-windows.tar.gz"
            },
            "32bit": {
                "url": "https://github.com/streamnative/pulsarctl/releases/download/v$version/pulsarctl-386-windows.tar.gz"
            }
        }
    }
}
