{
    "version": "1.37.0",
    "description": "The CLI for Qovery, a DevOps Automation Platform.",
    "homepage": "https://www.qovery.com/",
    "license": "Apache-2.0",
    "architecture": {
        "64bit": {
            "url": "https://github.com/Qovery/qovery-cli/releases/download/v1.37.0/qovery-cli_1.37.0_windows_amd64.zip",
            "hash": "39c5e848d8ec2f7113bdfd8cca8bd54f44edb104b1bf9d909ba2132e61c96784"
        },
        "arm64": {
            "url": "https://github.com/Qovery/qovery-cli/releases/download/v1.37.0/qovery-cli_1.37.0_windows_arm64.zip",
            "hash": "4bac7dad5bf8fa7fea2c4fd0c4c0243734aedbe210d768741e25297df0ab7fab"
        }
    },
    "bin": "qovery.exe",
    "checkver": {
        "github": "https://github.com/Qovery/qovery-cli"
    },
    "autoupdate": {
        "architecture": {
            "64bit": {
                "url": "https://github.com/Qovery/qovery-cli/releases/download/v$version/qovery-cli_$version_windows_amd64.zip"
            },
            "arm64": {
                "url": "https://github.com/Qovery/qovery-cli/releases/download/v$version/qovery-cli_$version_windows_arm64.zip"
            }
        },
        "hash": {
            "url": "$baseurl/checksums.txt"
        }
    }
}
