{
    "version": "7.90",
    "description": "Investigate performance and image quality of HW encoder (QSV) of Intel.",
    "homepage": "https://github.com/rigaya/QSVEnc",
    "license": {
        "identifier": "MIT",
        "url": "https://github.com/rigaya/QSVEnc/raw/refs/heads/master/license.txt"
    },
    "architecture": {
        "64bit": {
            "pre_install": "Get-ChildItem \"$dir\" 'QSVEncC64.exe' | Select-Object -First 1 | Rename-Item -NewName 'QSVEncC.exe'",
            "url": "https://github.com/rigaya/QSVEnc/releases/download/7.90/QSVEncC_7.90_x64.7z",
            "hash": "d5d0d896a8300ceb72f9a835d7b8c433ba2d85f158a2bf5c7f9cebc20afc97ba"
        },
        "32bit": {
            "url": "https://github.com/rigaya/QSVEnc/releases/download/7.90/QSVEncC_7.90_Win32.7z",
            "hash": "2ca844a67c80087b9461f841ef1f942679df9f56596028da8f12e03d893feb41"
        }
    },
    "bin": "QSVEncC.exe",
    "checkver": "github",
    "autoupdate": {
        "architecture": {
            "64bit": {
                "url": "https://github.com/rigaya/QSVEnc/releases/download/$version/QSVEncC_$version_x64.7z"
            },
            "32bit": {
                "url": "https://github.com/rigaya/QSVEnc/releases/download/$version/QSVEncC_$version_Win32.7z"
            }
        }
    }
}
