{
    "version": "1.12.2",
    "description": "Open source screen sharing for developers.",
    "homepage": "https://screego.net/",
    "license": "GPL-3.0-only",
    "architecture": {
        "64bit": {
            "url": "https://github.com/screego/server/releases/download/v1.12.2/screego_1.12.2_windows_amd64.zip",
            "hash": "f5926c2278b25110f337b744c59509873a863102728583bdef23bf15cb0b4fcf"
        },
        "32bit": {
            "url": "https://github.com/screego/server/releases/download/v1.12.2/screego_1.12.2_windows_i386.zip",
            "hash": "c5a33b0fb7efcb975c0b59947a0e9f9c2c171355ee3af9073b00aa56d82d324a"
        },
        "arm64": {
            "url": "https://github.com/screego/server/releases/download/v1.12.2/screego_1.12.2_windows_arm64.zip",
            "hash": "e51c0f8d5405c9920d8e9604f78c98bf7f2b775438ff29c4b0c4cf807730eddd"
        }
    },
    "bin": "screego.exe",
    "pre_install": "if (!(Test-Path \"$persist_dir\\screego.config\")) { Set-Content -Encoding ASCII -Path \"$dir\\screego.config\" -Value $null }",
    "persist": "screego.config",
    "checkver": {
        "github": "https://github.com/screego/server"
    },
    "autoupdate": {
        "architecture": {
            "64bit": {
                "url": "https://github.com/screego/server/releases/download/v$version/screego_$version_windows_amd64.zip"
            },
            "32bit": {
                "url": "https://github.com/screego/server/releases/download/v$version/screego_$version_windows_i386.zip"
            },
            "arm64": {
                "url": "https://github.com/screego/server/releases/download/v$version/screego_$version_windows_arm64.zip"
            }
        }
    }
}
