{
    "version": "1.563.0",
    "description": "Generate client SDKs in popular languages from your OpenAPI spec with Speakeasy.",
    "homepage": "https://speakeasy.com/",
    "license": "Elastic-2.0",
    "architecture": {
        "64bit": {
            "url": "https://github.com/speakeasy-api/speakeasy/releases/download/v1.563.0/speakeasy_windows_amd64.zip",
            "hash": "ebd66ae138a2614c494a1860e5270e8e4e67c2faf3ffa9a3451dc00c6f10729d"
        },
        "32bit": {
            "url": "https://github.com/speakeasy-api/speakeasy/releases/download/v1.563.0/speakeasy_windows_386.zip",
            "hash": "51221856ed998ae78c12cb9e34ae06f877bfe893237fcbafcb1f5a30a1c0afc8"
        },
        "arm64": {
            "url": "https://github.com/speakeasy-api/speakeasy/releases/download/v1.563.0/speakeasy_windows_arm64.zip",
            "hash": "7b7470623cff218dc4bd0d4e09a64f73decb164bdcfda973391cf08ad480f0c3"
        }
    },
    "bin": "speakeasy.exe",
    "checkver": {
        "github": "https://github.com/speakeasy-api/speakeasy"
    },
    "autoupdate": {
        "architecture": {
            "64bit": {
                "url": "https://github.com/speakeasy-api/speakeasy/releases/download/v$version/speakeasy_windows_amd64.zip"
            },
            "32bit": {
                "url": "https://github.com/speakeasy-api/speakeasy/releases/download/v$version/speakeasy_windows_386.zip"
            },
            "arm64": {
                "url": "https://github.com/speakeasy-api/speakeasy/releases/download/v$version/speakeasy_windows_arm64.zip"
            }
        },
        "hash": {
            "url": "$baseurl/checksums.txt"
        }
    }
}
