{
    "version": "1.636.2",
    "description": "Generate client SDKs in popular languages from your OpenAPI spec with Speakeasy.",
    "homepage": "https://speakeasy.com/",
    "license": "Elastic-2.0",
    "architecture": {
        "64bit": {
            "url": "https://github.com/speakeasy-api/speakeasy/releases/download/v1.636.2/speakeasy_windows_amd64.zip",
            "hash": "2cbd0ec96290c2de51e4d61643165c93dbf995386e874a4a5fbb78c568936e67"
        },
        "32bit": {
            "url": "https://github.com/speakeasy-api/speakeasy/releases/download/v1.636.2/speakeasy_windows_386.zip",
            "hash": "562868fd669f10c6e98066209bec048cb5d865e27bd02e0671007de38756741d"
        },
        "arm64": {
            "url": "https://github.com/speakeasy-api/speakeasy/releases/download/v1.636.2/speakeasy_windows_arm64.zip",
            "hash": "000a2fa6242ee61a591ef70a1d7af3c078607c0f018535e76915bd331ab13857"
        }
    },
    "bin": "speakeasy.exe",
    "checkver": {
        "github": "https://github.com/speakeasy-api/speakeasy"
    },
    "autoupdate": {
        "architecture": {
            "64bit": {
                "url": "https://github.com/speakeasy-api/speakeasy/releases/download/v$version/speakeasy_windows_amd64.zip"
            },
            "32bit": {
                "url": "https://github.com/speakeasy-api/speakeasy/releases/download/v$version/speakeasy_windows_386.zip"
            },
            "arm64": {
                "url": "https://github.com/speakeasy-api/speakeasy/releases/download/v$version/speakeasy_windows_arm64.zip"
            }
        },
        "hash": {
            "url": "$baseurl/checksums.txt"
        }
    }
}
