{
    "version": "b480-b87fe13",
    "description": "(CPU Backend) stable-diffusion.cpp enables inference of Stable Diffusion and Flux in pure C/C++.",
    "homepage": "https://github.com/leejet/stable-diffusion.cpp",
    "license": "MIT",
    "architecture": {
        "64bit": {
            "url": "https://github.com/leejet/stable-diffusion.cpp/releases/download/master-480-b87fe13/sd-master-b87fe13-bin-win-avx2-x64.zip",
            "hash": "2736a821500d8c65a27dc53f851e36e58c541cd4e69f6b34363b5fc3471e7a6e"
        }
    },
    "bin": [
        "sd-cli.exe",
        "sd-server.exe"
    ],
    "checkver": {
        "url": "https://github.com/leejet/stable-diffusion.cpp/releases.atom",
        "regex": "Repository/\\d+/master-(?<build>\\d+)-(?<commit>[0-9a-f]{7})<",
        "replace": "b${build}-${commit}"
    },
    "autoupdate": {
        "architecture": {
            "64bit": {
                "url": "https://github.com/leejet/stable-diffusion.cpp/releases/download/master-$matchBuild-$matchCommit/sd-master-$matchCommit-bin-win-avx2-x64.zip"
            }
        }
    }
}
