{
    "version": "0.7.7",
    "description": "A powerful toolkit that provides a TOML Formatter, Linter, and Language Server to help you maintain clean and consistent TOML files.",
    "homepage": "https://tombi-toml.github.io/tombi/",
    "license": "MIT",
    "architecture": {
        "64bit": {
            "url": "https://github.com/tombi-toml/tombi/releases/download/v0.7.7/tombi-cli-0.7.7-x86_64-pc-windows-msvc.zip",
            "hash": "ab073e78646b1be8116a093ffdb5581d799b0d8bb78bcf9fd6af3c49ff243043"
        },
        "arm64": {
            "url": "https://github.com/tombi-toml/tombi/releases/download/v0.7.7/tombi-cli-0.7.7-aarch64-pc-windows-msvc.zip",
            "hash": "4f56a889eb540d41d6d3ea973879a5591adc96a7f978e37bd65cd2573065e3c9"
        }
    },
    "bin": "tombi.exe",
    "checkver": {
        "github": "https://github.com/tombi-toml/tombi"
    },
    "autoupdate": {
        "architecture": {
            "64bit": {
                "url": "https://github.com/tombi-toml/tombi/releases/download/v$version/tombi-cli-$version-x86_64-pc-windows-msvc.zip"
            },
            "arm64": {
                "url": "https://github.com/tombi-toml/tombi/releases/download/v$version/tombi-cli-$version-aarch64-pc-windows-msvc.zip"
            }
        }
    }
}
