{
    "version": "4.6.4",
    "description": "A powerful, multifunctional, and open-source DICOM viewer.",
    "homepage": "https://weasis.org/",
    "license": "EPL-2.0|Apache-2.0",
    "architecture": {
        "64bit": {
            "url": "https://github.com/nroduit/Weasis/releases/download/v4.6.4/Weasis-4.6.4-x86-64.msi",
            "hash": "3e00efa199ca9aa4a49740490a8a7b83becd0cf6b8cbe811fd70fc3aac36d568"
        }
    },
    "extract_dir": "Weasis",
    "shortcuts": [
        [
            "Weasis.exe",
            "Weasis"
        ],
        [
            "Dicomizer.exe",
            "Weasis Dicomizer"
        ]
    ],
    "checkver": {
        "github": "https://github.com/nroduit/Weasis/"
    },
    "autoupdate": {
        "architecture": {
            "64bit": {
                "url": "https://github.com/nroduit/Weasis/releases/download/v$version/Weasis-$version-x86-64.msi"
            }
        }
    }
}
