{
    "version": "9.0-beta.15",
    "description": "Open-source reference management software to manage bibliographic data and related research materials.",
    "homepage": "https://www.zotero.org/",
    "license": "AGPL-3.0-only",
    "architecture": {
        "64bit": {
            "url": "https://download.zotero.org/client/beta/9.0-beta.15%2B81591eb89/Zotero-9.0-beta.15%2B81591eb89_x64_setup.exe#/dl.7z",
            "hash": "6efb89bcaa64be942e2760381d1d603ac0f81db39ff260ea7b76d81c36fe2bc6"
        },
        "32bit": {
            "url": "https://download.zotero.org/client/beta/9.0-beta.15%2B81591eb89/Zotero-9.0-beta.15%2B81591eb89_win32_setup.exe#/dl.7z",
            "hash": "493c662d7010461fb2a12091b9188865e04219a491b8920c80f2bfd2b357a5dd"
        }
    },
    "extract_dir": "core",
    "bin": "zotero.exe",
    "shortcuts": [
        [
            "zotero.exe",
            "Zotero"
        ]
    ],
    "notes": [
        "To register the 'zotero://' URL protocol, run:",
        "$dir\\install-zotero-url-protocol.ps1",
        "",
        "Existing 'zotero://' URL protocol may be overwrite.",
        "",
        "To unregister the 'zotero://' URL protocol, run:",
        "$dir\\uninstall-zotero-url-protocol.ps1"
    ],
    "post_install": [
        "if (!$bucket) { return }",
        "$scriptsDir = \"$bucketsdir\\$bucket\\scripts\"",
        "Get-ChildItem \"$scriptsDir\\zotero\\*.ps1\" | ForEach-Object {",
        "    $content = Get-Content $_",
        "    $content = $content.Replace('REPLACE_HERE', $dir)",
        "    if ($global) { $content = $content.Replace('HKCU', 'HKLM') }",
        "    Set-Content \"$dir\\$($_.Name)\" $content -Encoding 'utf8' -Force",
        "}"
    ],
    "pre_uninstall": [
        "if ($cmd -eq 'uninstall') {",
        "    Write-Host 'Unregistering the ''zotero://'' URL protocol...'",
        "    Remove-Item 'HKCU:\\SOFTWARE\\Classes\\zotero', 'HKLM:\\SOFTWARE\\Classes\\zotero' -ErrorAction 'SilentlyContinue' -Recurse -Force",
        "    Write-Host 'Done!'",
        "}"
    ],
    "checkver": {
        "script": [
            "try { $detail = Invoke-WebRequest 'https://www.zotero.org/download/client/dl?platform=win-x64-zip&channel=beta' -MaximumRedirection 0 -ErrorAction Ignore } catch { $_.Exception.Response }",
            "return $detail.Headers.Location"
        ],
        "regex": "Zotero-([\\d.]+-beta[\\d.]+)%2B(?<commit>[\\da-f]+)"
    },
    "autoupdate": {
        "architecture": {
            "64bit": {
                "url": "https://download.zotero.org/client/beta/$version%2B$matchCommit/Zotero-$version%2B$matchCommit_x64_setup.exe#/dl.7z"
            },
            "32bit": {
                "url": "https://download.zotero.org/client/beta/$version%2B$matchCommit/Zotero-$version%2B$matchCommit_win32_setup.exe#/dl.7z"
            }
        }
    }
}
